[{"text": "Ahuachap\u00e1n", "value": "SV-AH"}, {"text": "Caba\u00f1as", "value": "SV-CA"}, {"text": "Chalatenango", "value": "SV-CH"}, {"text": "Cuscatl\u00e1n", "value": "SV-CU"}, {"text": "La Libertad", "value": "SV-LI"}, {"text": "Moraz\u00e1n", "value": "SV-MO"}, {"text": "La Paz", "value": "SV-PA"}, {"text": "Santa Ana", "value": "SV-SA"}, {"text": "San Miguel", "value": "SV-SM"}, {"text": "Sonsonate", "value": "SV-SO"}, {"text": "San Salvador", "value": "SV-SS"}, {"text": "San Vicente", "value": "SV"}, {"text": "La Uni\u00f3n", "value": "SV-UN"}, {"text": "Usulut\u00e1n", "value": "SV-US"}]