[{"text": "Ajdov\u0161cina", "value": "SI-001"}, {"text": "Beltinci", "value": "SI-002"}, {"text": "Bled", "value": "SI-003"}, {"text": "Bohinj", "value": "SI-004"}, {"text": "Borovnica", "value": "SI-005"}, {"text": "Bovec", "value": "SI-006"}, {"text": "Brda", "value": "SI-007"}, {"text": "Brezovica", "value": "SI-008"}, {"text": "Bre\u017eice", "value": "SI-009"}, {"text": "Ti\u0161ina", "value": "SI-010"}, {"text": "Celje", "value": "SI-011"}, {"text": "Cerklje na Gorenjskem", "value": "SI-012"}, {"text": "Cerknica", "value": "SI-013"}, {"text": "Cerkno", "value": "SI-014"}, {"text": "Cren\u0161ovci", "value": "SI-015"}, {"text": "Crna na Koro\u0161kem", "value": "SI-016"}, {"text": "Crnomelj", "value": "SI-017"}, {"text": "Destrnik", "value": "SI-018"}, {"text": "Divaca", "value": "SI-019"}, {"text": "Dobrepolje", "value": "SI-020"}, {"text": "Dobrova-Polhov Gradec", "value": "SI-021"}, {"text": "Dol pri Ljubljani", "value": "SI-022"}, {"text": "Dom\u017eale", "value": "SI-023"}, {"text": "Dornava", "value": "SI-024"}, {"text": "Dravograd", "value": "SI-025"}, {"text": "Duplek", "value": "SI-026"}, {"text": "Gorenja vas-Poljane", "value": "SI-027"}, {"text": "Gori\u0161nica", "value": "SI-028"}, {"text": "Gornja Radgona", "value": "SI-029"}, {"text": "Gornji Grad", "value": "SI-030"}, {"text": "Gornji Petrovci", "value": "SI-031"}, {"text": "Grosuplje", "value": "SI-032"}, {"text": "\u0160alovci", "value": "SI-033"}, {"text": "Hrastnik", "value": "SI-034"}, {"text": "Hrpelje-Kozina", "value": "SI-035"}, {"text": "Idrija", "value": "SI-036"}, {"text": "Ig", "value": "SI-037"}, {"text": "Ilirska Bistrica", "value": "SI-038"}, {"text": "Ivancna Gorica", "value": "SI-039"}, {"text": "Izola/Isola", "value": "SI-040"}, {"text": "Jesenice", "value": "SI-041"}, {"text": "Jur\u0161inci", "value": "SI-042"}, {"text": "Kamnik", "value": "SI-043"}, {"text": "Kanal", "value": "SI-044"}, {"text": "Kidricevo", "value": "SI-045"}, {"text": "Kobarid", "value": "SI-046"}, {"text": "Kobilje", "value": "SI-047"}, {"text": "Kocevje", "value": "SI-048"}, {"text": "Komen", "value": "SI-049"}, {"text": "Koper/Capodistria", "value": "SI-050"}, {"text": "Kozje", "value": "SI-051"}, {"text": "Kranj", "value": "SI-052"}, {"text": "Kranjska Gora", "value": "SI-053"}, {"text": "Kr\u0161ko", "value": "SI-054"}, {"text": "Kungota", "value": "SI-055"}, {"text": "Kuzma", "value": "SI-056"}, {"text": "La\u0161ko", "value": "SI-057"}, {"text": "Lenart", "value": "SI-058"}, {"text": "Lendava/Lendva", "value": "SI-059"}, {"text": "Litija", "value": "SI-060"}, {"text": "Ljubljana", "value": "SI-061"}, {"text": "Ljubno", "value": "SI-062"}, {"text": "Ljutomer", "value": "SI-063"}, {"text": "Logatec", "value": "SI-064"}, {"text": "Lo\u0161ka dolina", "value": "SI-065"}, {"text": "Lo\u0161ki Potok", "value": "SI-066"}, {"text": "Luce", "value": "SI-067"}, {"text": "Lukovica", "value": "SI-068"}, {"text": "Maj\u0161perk", "value": "SI-069"}, {"text": "Maribor", "value": "SI-070"}, {"text": "Medvode", "value": "SI-071"}, {"text": "Menge\u0161", "value": "SI-072"}, {"text": "Metlika", "value": "SI-073"}, {"text": "Me\u017eica", "value": "SI-074"}, {"text": "Miren-Kostanjevica", "value": "SI-075"}, {"text": "Mislinja", "value": "SI-076"}, {"text": "Moravce", "value": "SI-077"}, {"text": "Moravske Toplice", "value": "SI-078"}, {"text": "Mozirje", "value": "SI-079"}, {"text": "Murska Sobota", "value": "SI-080"}, {"text": "Muta", "value": "SI-081"}, {"text": "Naklo", "value": "SI-082"}, {"text": "Nazarje", "value": "SI-083"}, {"text": "Nova Gorica", "value": "SI-084"}, {"text": "Novo mesto", "value": "SI-085"}, {"text": "Odranci", "value": "SI-086"}, {"text": "Ormo\u017e", "value": "SI-087"}, {"text": "Osilnica", "value": "SI-088"}, {"text": "Pesnica", "value": "SI-089"}, {"text": "Piran/Pirano", "value": "SI-090"}, {"text": "Pivka", "value": "SI-091"}, {"text": "Podcetrtek", "value": "SI-092"}, {"text": "Podvelka", "value": "SI-093"}, {"text": "Postojna", "value": "SI-094"}, {"text": "Preddvor", "value": "SI-095"}, {"text": "Ptuj", "value": "SI-096"}, {"text": "Puconci", "value": "SI-097"}, {"text": "Race-Fram", "value": "SI-098"}, {"text": "Radece", "value": "SI-099"}, {"text": "Radenci", "value": "SI-100"}, {"text": "Radlje ob Dravi", "value": "SI-101"}, {"text": "Radovljica", "value": "SI-102"}, {"text": "Ravne na Koro\u0161kem", "value": "SI-103"}, {"text": "Ribnica", "value": "SI-104"}, {"text": "Roga\u0161ovci", "value": "SI-105"}, {"text": "Roga\u0161ka Slatina", "value": "SI-106"}, {"text": "Rogatec", "value": "SI-107"}, {"text": "Ru\u0161e", "value": "SI-108"}, {"text": "Semic", "value": "SI-109"}, {"text": "Sevnica", "value": "SI-110"}, {"text": "Se\u017eana", "value": "SI-111"}, {"text": "Slovenj Gradec", "value": "SI-112"}, {"text": "Slovenska Bistrica", "value": "SI-113"}, {"text": "Slovenske Konjice", "value": "SI-114"}, {"text": "Star\u0161e", "value": "SI-115"}, {"text": "Sveti Jurij", "value": "SI-116"}, {"text": "\u0160encur", "value": "SI-117"}, {"text": "\u0160entilj", "value": "SI-118"}, {"text": "\u0160entjernej", "value": "SI-119"}, {"text": "\u0160entjur pri Celju", "value": "SI-120"}, {"text": "\u0160kocjan", "value": "SI-121"}, {"text": "\u0160kofja Loka", "value": "SI-122"}, {"text": "\u0160kofljica", "value": "SI-123"}, {"text": "\u0160marje pri Jel\u0161ah", "value": "SI-124"}, {"text": "\u0160martno ob Paki", "value": "SI-125"}, {"text": "\u0160o\u0161tanj", "value": "SI-126"}, {"text": "\u0160tore", "value": "SI-127"}, {"text": "Tolmin", "value": "SI-128"}, {"text": "Trbovlje", "value": "SI-129"}, {"text": "Trebnje", "value": "SI-130"}, {"text": "Tr\u017eic", "value": "SI-131"}, {"text": "Turni\u0161ce", "value": "SI-132"}, {"text": "Velenje", "value": "SI-133"}, {"text": "Velike La\u0161ce", "value": "SI-134"}, {"text": "Videm", "value": "SI-135"}, {"text": "Vipava", "value": "SI-136"}, {"text": "Vitanje", "value": "SI-137"}, {"text": "Vodice", "value": "SI-138"}, {"text": "Vojnik", "value": "SI-139"}, {"text": "Vrhnika", "value": "SI-140"}, {"text": "Vuzenica", "value": "SI-141"}, {"text": "Zagorje ob Savi", "value": "SI-142"}, {"text": "Zavrc", "value": "SI-143"}, {"text": "Zrece", "value": "SI-144"}, {"text": "\u017delezniki", "value": "SI-146"}, {"text": "\u017diri", "value": "SI-147"}, {"text": "Benedikt", "value": "SI-148"}, {"text": "Bistrica ob Sotli", "value": "SI-149"}, {"text": "Bloke", "value": "SI-150"}, {"text": "Braslovce", "value": "SI-151"}, {"text": "Cankova", "value": "SI-152"}, {"text": "Cerkvenjak", "value": "SI-153"}, {"text": "Dobje", "value": "SI-154"}, {"text": "Dobrna", "value": "SI-155"}, {"text": "Dobrovnik/Dobronak", "value": "SI-156"}, {"text": "Dolenjske Toplice", "value": "SI-157"}, {"text": "Grad", "value": "SI-158"}, {"text": "Hajdina", "value": "SI-159"}, {"text": "Hoce-Slivnica", "value": "SI-160"}, {"text": "Hodo\u0161/Hodos", "value": "SI-161"}, {"text": "Horjul", "value": "SI-162"}, {"text": "Jezersko", "value": "SI-163"}, {"text": "Komenda", "value": "SI-164"}, {"text": "Kostel", "value": "SI-165"}, {"text": "Kri\u017eevci", "value": "SI-166"}, {"text": "Lovrenc na Pohorju", "value": "SI-167"}, {"text": "Markovci", "value": "SI-168"}, {"text": "Miklav\u017e na Dravskem polju", "value": "SI-169"}, {"text": "Mirna Pec", "value": "SI-170"}, {"text": "Oplotnica", "value": "SI-171"}, {"text": "Podlehnik", "value": "SI-172"}, {"text": "Polzela", "value": "SI-173"}, {"text": "Prebold", "value": "SI-174"}, {"text": "Prevalje", "value": "SI-175"}, {"text": "Razkri\u017eje", "value": "SI-176"}, {"text": "Ribnica na Pohorju", "value": "SI-177"}, {"text": "Selnica ob Dravi", "value": "SI-178"}, {"text": "Sodra\u017eica", "value": "SI-179"}, {"text": "Solcava", "value": "SI-180"}, {"text": "Sveta Ana", "value": "SI-181"}, {"text": "Sveti Andra\u017e v Slovenskih goricah", "value": "SI-182"}, {"text": "\u0160empeter-Vrtojba", "value": "SI-183"}, {"text": "Tabor", "value": "SI-184"}, {"text": "Trnovska vas", "value": "SI-185"}, {"text": "Trzin", "value": "SI-186"}, {"text": "Velika Polana", "value": "SI-187"}, {"text": "Ver\u017eej", "value": "SI-188"}, {"text": "Vransko", "value": "SI-189"}, {"text": "\u017dalec", "value": "SI-190"}, {"text": "\u017detale", "value": "SI-191"}, {"text": "\u017dirovnica", "value": "SI-192"}, {"text": "\u017du\u017eemberk", "value": "SI-193"}, {"text": "\u0160martno pri Litiji", "value": "SI-194"}]